pybomberman/__init__.py
pybomberman-0.0.2.dist-info/LICENSE
pybomberman-0.0.2.dist-info/METADATA
pybomberman-0.0.2.dist-info/WHEEL
pybomberman-0.0.2.dist-info/top_level.txt
pybomberman-0.0.2.dist-info/RECORD
