Metadata-Version: 2.1
Name: pybomberman
Version: 0.0.2
Summary: Bomberman game and framework implementation in python
Home-page: https://github.com/pybomberman/pybomberman
Author: pybomberman Staff
Author-email: author@example.com
License: UNKNOWN
Platform: UNKNOWN
Classifier: Programming Language :: Python :: 3
Classifier: License :: OSI Approved :: MIT License
Classifier: Operating System :: OS Independent
Requires-Python: >=3.6
